{
    "title": "Safe Testing. (arXiv:1906.07801v5 [math.ST] UPDATED)",
    "abstract": "We develop the theory of hypothesis testing based on the e-value, a notion of evidence that, unlike the p-value, allows for effortlessly combining results from several studies in the common scenario where the decision to perform a new study may depend on previous outcomes. Tests based on e-values are safe, i.e. they preserve Type-I error guarantees, under such optional continuation. We define growth-rate optimality (GRO) as an analogue of power in an optional continuation context, and we show how to construct GRO e-variables for general testing problems with composite null and alternative, emphasizing models with nuisance parameters. GRO e-values take the form of Bayes factors with special priors. We illustrate the theory using several classic examples including a one-sample safe t-test and the 2 x 2 contingency table. Sharing Fisherian, Neymanian and Jeffreys-Bayesian interpretations, e-values may provide a methodology acceptable to adherents of all three schools.",
    "link": "http://arxiv.org/abs/1906.07801",
    "raw_ret": "{\n    \"translated_title\": \"安全检验 (arXiv:1906.07801v5 [math.ST] UPDATED)\",\n    \"translated_abstract\": \"我们开发了基于E值的假设检验理论，E值是一种证据概念，与p值不同，它允许在新研究的决定可能取决于先前结果的常见情况下轻松地结合几个研究的结果。基于E值的测试是安全的，即在这种可选继续的情况下保持类型I错误的保证。我们定义了生长速率最优（GRO）作为可选继续情境中功率的类比，并展示了如何针对具有复合零和替代的常规测试问题构建GRO E变量，强调具有困扰参数模型。GRO E值采用特殊先验的贝叶斯因子形式。我们使用几个经典的例子来说明该理论，包括单样本安全t检验和2 x 2列联表。共享费舍尔、尼曼和杰弗里斯-贝叶斯解释，e值可以为所有三个学派的信奉者提供可接受的方法论。\",\n    \"tldr\": \"该论文开发了一种基于E值的假设检验理论，这种方法可以在多个研究的结果中轻松结合数据，并且在可选的继续研究的情况下保持类型I错误的保证。此外，论文还引入了生长速率最优（GRO）概念作为功率的类比，并给出了构建GRO E变量的方法。\"",
    "total_tokens": 917
}